tmts_distributions/Binomialdistribution.py
tmts_distributions/Gaussiandistribution.py
tmts_distributions/Generaldistribution.py
tmts_distributions/__init__.py
tmts_distributions-0.1.1.dist-info/METADATA
tmts_distributions-0.1.1.dist-info/WHEEL
tmts_distributions-0.1.1.dist-info/license.txt
tmts_distributions-0.1.1.dist-info/top_level.txt
tmts_distributions-0.1.1.dist-info/RECORD
