Metadata-Version: 2.1
Name: tmts-distributions
Version: 0.1.1
Summary: Gaussian and binomial distributions
Author: Timotius Marselo
Author-email: timotiusmarselo@gmail.com
License-File: license.txt
